odoo/addons/avoid_assignation_notification/README.rst
odoo/addons/avoid_assignation_notification/__init__.py
odoo/addons/avoid_assignation_notification/__manifest__.py
odoo/addons/avoid_assignation_notification/i18n/es.po
odoo/addons/avoid_assignation_notification/models/__init__.py
odoo/addons/avoid_assignation_notification/models/mail_thread.py
odoo/addons/avoid_assignation_notification/models/res_company.py
odoo/addons/avoid_assignation_notification/models/res_config_settings.py
odoo/addons/avoid_assignation_notification/static/description/icon.png
odoo/addons/avoid_assignation_notification/views/res_config_settings_views.xml
odoo14_addon_avoid_assignation_notification-14.0.1.0.0.dist-info/METADATA
odoo14_addon_avoid_assignation_notification-14.0.1.0.0.dist-info/WHEEL
odoo14_addon_avoid_assignation_notification-14.0.1.0.0.dist-info/top_level.txt
odoo14_addon_avoid_assignation_notification-14.0.1.0.0.dist-info/RECORD
